{"list":{"id":"362989","post_type":"franchise-list","post_title":"Fortune 500 2001","post_content":"","post_excerpt":"","year":"2001","short_name":"Fortune 500 2001","methodology":"","fortune_intro_title":"","top_stories":[],"franchise_type":"","filters":{"Industry":{"61":"Advertising, marketing","40":"Aerospace and Defense","42":"Airlines","41":"Apparel","55":"Automotive Retailing, Services","47":"Beverages","54":"Building Materials, Glass","5":"Chemicals","2":"Commercial Banks","11":"Computer And Data Services","46":"Computer Peripherals","35":"Computers, Office Equipment","36":"Computer Software","14":"Diversified Financials","30":"Diversified Outsourcing Services","10":"Electronics, Electrical Equip.","25":"Energy","6":"Engineering, Construction","60":"Entertainment","17":"Food and Drug Stores","18":"Food Consumer Products","34":"Food Production","39":"Food Services","16":"Forest and Paper Products","58":"Furniture","23":"General Merchandisers","3":"Health Care","29":"Hotels, Casinos, Resorts","4":"Industrial and Farm Equipment","33":"Insurance: Life, Health (Mutual)","20":"Insurance: Life, Health (stock)","57":"Insurance: Property and Casualty (Mutual)","12":"Insurance: Property and Casualty (Stock)","56":"Mail, Package, and Freight Delivery","51":"Medical Products and Equipment","21":"Metal Products","32":"Metals","24":"Mining, Crude-Oil Production","7":"Motor Vehicles and Parts","38":"Network and Other Communications Equipment","68":"Oilfield Services","22":"Petroleum Refining","37":"Pharmaceuticals","50":"Pipelines","13":"Publishing, Printing","64":"Railroads","63":"Real estate","49":"Rubber and Plastic Products","45":"Savings Institutions","28":"Scientific,Photographic and Control Equipment","27":"Securities","9":"Semiconductors and Other Electronic Components","44":"Soaps, Cosmetics","0":"Specialty Retailers","8":"Telecommunications","53":"Temporary Help","52":"Textiles","59":"Tobacco","67":"Toys, Sporting Goods","66":"Transportation and Logistics","62":"Transportation Equipment","26":"Trucking, Truck Leasing","1":"Utilities: Gas and Electric","65":"Waste Management","69":"Wholesalers","15":"Wholesalers: Diversified","19":"Wholesalers: Electronics and Office Equipment","31":"Wholesalers: Food and Grocery","48":"Wholesalers: Health Care","43":"zMiscellaneous"},"Headquarters State":{"23":"AL","27":"AR","20":"AZ","0":"CA","22":"CO","11":"CT","26":"DC","38":"DE","9":"FL","10":"GA","43":"HI","34":"IA","40":"ID","3":"IL","21":"IN","33":"KS","25":"KY","37":"LA","16":"MA","18":"MD","42":"ME","7":"MI","8":"MN","14":"MO","46":"MS","15":"NC","45":"ND","29":"NE","36":"NH","6":"NJ","41":"NM","24":"NV","1":"NY","4":"OH","31":"OK","28":"OR","5":"PA","44":"PR","30":"RI","32":"SC","39":"SD","19":"TN","2":"TX","35":"UT","13":"VA","17":"WA","12":"WI"}},"sort":["Rank","Revenues"],"translations":{"Headquarters State":{"AL":"Alabama","AK":"Alaska","AZ":"Arizona","AR":"Arkansas","CA":"California","CO":"Colorado","CT":"Connecticut","DE":"Delaware","DC":"District Of Columbia","FL":"Florida","GA":"Georgia","HI":"Hawaii","ID":"Idaho","IL":"Illinois","IN":"Indiana","IA":"Iowa","KS":"Kansas","KY":"Kentucky","LA":"Louisiana","ME":"Maine","MD":"Maryland","MA":"Massachusetts","MI":"Michigan","MN":"Minnesota","MS":"Mississippi","MO":"Missouri","MT":"Montana","NE":"Nebraska","NV":"Nevada","NH":"New Hampshire","NJ":"New Jersey","NM":"New Mexico","NY":"New York","NC":"North Carolina","ND":"North Dakota","OH":"Ohio","OK":"Oklahoma","OR":"Oregon","PA":"Pennsylvania","PR":"Puerto Rico","RI":"Rhode Island","SC":"South Carolina","SD":"South Dakota","TN":"Tennessee","TX":"Texas","UT":"Utah","VT":"Vermont","VA":"Virginia","WA":"Washington","WV":"West Virginia","WI":"Wisconsin","WY":"Wyoming"}},"social":{"encoded_url":"http%3A%2F%2Ffortune.com%2Ffortune500%2F2001%2F","encoded_shortlink":"http%3A%2F%2Fwp.me%2Fp4kUAt-1wqF","twitter_text":"Fortune 500 2001","encoded_title":"Fortune+500+2001"}},"articles":[{"id":363033,"post_type":"franchise-list-item","url":"\/fortune500\/2001\/goldman-sachs-group-inc-42\/","title":"Goldman Sachs Group, Inc.","list_title":"Fortune 500 2001","content":"","rank":"42","thumbnail":"","featured_image":"","tables":"","buttons":"","ticker":"\u003Ctable class=\u0022tickershortcode company-market-data trend-wrapper unprocessed neutral\u0022 data-symbol=\u0022gs\u0022\u003E\n\t\t\t\t\u003Ctr\u003E\n\t\t\t\t\t\u003Ctd\u003E\u003Cspan class=\u0022ticker\u0022\u003EGS\u003C\/span\u003E\u003C\/td\u003E\n\t\t\t\t\t\u003Ctd\u003E\u003Cspan class=\u0022tickerdata last\u0022\u003E\u003C\/span\u003E\u003Cspan class=\u0022change long\u0022\u003E\u003C\/span\u003E\u003C\/td\u003E\n\t\t\t\t\t\u003Ctd\u003E\u003Ctime class=\u0022tickerdata time\u0022\u003E\u003C\/time\u003E\u003C\/td\u003E\n\t\t\t\t\u003C\/tr\u003E\n\t\t\t\u003C\/table\u003E","ticker_text":"gs","highlights":{"Rank":"42","Previous Rank":"54","CEO":"Henry M. Paulson Jr.","Address":"6501 Legacy Dr., Plano, TX 75024","Website":"www.gs.com"},"linkedin":"","footnotes":"","ordering":"","year":"2001","franchise_name":"Fortune 500","right_rail_layout":"default","seo":{"seo_title":"Goldman Sachs Group, Inc. - Fortune 500 2001 - Fortune","seo_description":"","seo_keywords":"","seo_news_keywords":"","seo_additional_meta":""},"social":{"encoded_url":"http%3A%2F%2Ffortune.com%2Ffortune500%2F2001%2Fgoldman-sachs-group-inc-42%2F","encoded_shortlink":"http%3A%2F%2Fwp.me%2Fp4kUAt-1wrn","twitter_text":"Goldman Sachs Group, Inc. on the Fortune 500 2001","facebook_desc":"","facebook_title":"Goldman Sachs Group, Inc. - Fortune 500 2001 - Fortune","encoded_title":"Goldman+Sachs+Group%2C+Inc.+-+Fortune+500+2001+-+Fortune"}},{"id":363034,"post_type":"franchise-list-item","url":"\/fortune500\/2001\/j-c-penney-company-inc-43\/","title":"J.C. Penney Company, Inc.","list_title":"Fortune 500 2001","content":"","rank":"43","thumbnail":"","featured_image":"","tables":"","buttons":"","ticker":"\u003Ctable class=\u0022tickershortcode company-market-data trend-wrapper unprocessed neutral\u0022 data-symbol=\u0022jcp\u0022\u003E\n\t\t\t\t\u003Ctr\u003E\n\t\t\t\t\t\u003Ctd\u003E\u003Cspan class=\u0022ticker\u0022\u003EJCP\u003C\/span\u003E\u003C\/td\u003E\n\t\t\t\t\t\u003Ctd\u003E\u003Cspan class=\u0022tickerdata last\u0022\u003E\u003C\/span\u003E\u003Cspan class=\u0022change long\u0022\u003E\u003C\/span\u003E\u003C\/td\u003E\n\t\t\t\t\t\u003Ctd\u003E\u003Ctime class=\u0022tickerdata time\u0022\u003E\u003C\/time\u003E\u003C\/td\u003E\n\t\t\t\t\u003C\/tr\u003E\n\t\t\t\u003C\/table\u003E","ticker_text":"jcp","highlights":{"Rank":"43","Previous Rank":"36","CEO":"Allen Questrom","Address":"55 Glenlake Pkwy. N.E., Atlanta, GA 30328","Website":"www.jcpenney.com"},"linkedin":"","footnotes":"","ordering":"","year":"2001","franchise_name":"Fortune 500","right_rail_layout":"default","seo":{"seo_title":"J.C. Penney Company, Inc. - Fortune 500 2001 - Fortune","seo_description":"","seo_keywords":"","seo_news_keywords":"","seo_additional_meta":""},"social":{"encoded_url":"http%3A%2F%2Ffortune.com%2Ffortune500%2F2001%2Fj-c-penney-company-inc-43%2F","encoded_shortlink":"http%3A%2F%2Fwp.me%2Fp4kUAt-1wro","twitter_text":"J.C. Penney Company, Inc. on the Fortune 500 2001","facebook_desc":"","facebook_title":"J.C. Penney Company, Inc. - Fortune 500 2001 - Fortune","encoded_title":"J.C.+Penney+Company%2C+Inc.+-+Fortune+500+2001+-+Fortune"}},{"id":363035,"post_type":"franchise-list-item","url":"\/fortune500\/2001\/conoco-44\/","title":"Conoco","list_title":"Fortune 500 2001","content":"","rank":"44","thumbnail":"","featured_image":"","tables":"","buttons":"","ticker":"\u003Ctable class=\u0022tickershortcode company-market-data trend-wrapper unprocessed neutral\u0022 data-symbol=\u0022coc b\u0022\u003E\n\t\t\t\t\u003Ctr\u003E\n\t\t\t\t\t\u003Ctd\u003E\u003Cspan class=\u0022ticker\u0022\u003ECOC B\u003C\/span\u003E\u003C\/td\u003E\n\t\t\t\t\t\u003Ctd\u003E\u003Cspan class=\u0022tickerdata last\u0022\u003E\u003C\/span\u003E\u003Cspan class=\u0022change long\u0022\u003E\u003C\/span\u003E\u003C\/td\u003E\n\t\t\t\t\t\u003Ctd\u003E\u003Ctime class=\u0022tickerdata time\u0022\u003E\u003C\/time\u003E\u003C\/td\u003E\n\t\t\t\t\u003C\/tr\u003E\n\t\t\t\u003C\/table\u003E","ticker_text":"coc b","highlights":{"Rank":"44","Previous Rank":"74","CEO":"Archie W. Dunham","Address":"2775 Sanders Rd., Northbrook, IL 60062","Website":"www.conoco.com"},"linkedin":"","footnotes":"","ordering":"","year":"2001","franchise_name":"Fortune 500","right_rail_layout":"default","seo":{"seo_title":"Conoco - Fortune 500 2001 - Fortune","seo_description":"","seo_keywords":"","seo_news_keywords":"","seo_additional_meta":""},"social":{"encoded_url":"http%3A%2F%2Ffortune.com%2Ffortune500%2F2001%2Fconoco-44%2F","encoded_shortlink":"http%3A%2F%2Fwp.me%2Fp4kUAt-1wrp","twitter_text":"Conoco on the Fortune 500 2001","facebook_desc":"","facebook_title":"Conoco - Fortune 500 2001 - Fortune","encoded_title":"Conoco+-+Fortune+500+2001+-+Fortune"}},{"id":363036,"post_type":"franchise-list-item","url":"\/fortune500\/2001\/costco-wholesale-corporation-45\/","title":"Costco Wholesale Corporation","list_title":"Fortune 500 2001","content":"","rank":"45","thumbnail":"","featured_image":"","tables":"","buttons":"","ticker":"\u003Ctable class=\u0022tickershortcode company-market-data trend-wrapper unprocessed neutral\u0022 data-symbol=\u0022cost\u0022\u003E\n\t\t\t\t\u003Ctr\u003E\n\t\t\t\t\t\u003Ctd\u003E\u003Cspan class=\u0022ticker\u0022\u003ECOST\u003C\/span\u003E\u003C\/td\u003E\n\t\t\t\t\t\u003Ctd\u003E\u003Cspan class=\u0022tickerdata last\u0022\u003E\u003C\/span\u003E\u003Cspan class=\u0022change long\u0022\u003E\u003C\/span\u003E\u003C\/td\u003E\n\t\t\t\t\t\u003Ctd\u003E\u003Ctime class=\u0022tickerdata time\u0022\u003E\u003C\/time\u003E\u003C\/td\u003E\n\t\t\t\t\u003C\/tr\u003E\n\t\t\t\u003C\/table\u003E","ticker_text":"cost","highlights":{"Rank":"45","Previous Rank":"44","CEO":"James D. Sinegal","Address":"200 Wilmot Rd., Deerfield, IL 60015","Website":"www.costco.com"},"linkedin":"","footnotes":"","ordering":"","year":"2001","franchise_name":"Fortune 500","right_rail_layout":"default","seo":{"seo_title":"Costco Wholesale Corporation - Fortune 500 2001 - Fortune","seo_description":"","seo_keywords":"","seo_news_keywords":"","seo_additional_meta":""},"social":{"encoded_url":"http%3A%2F%2Ffortune.com%2Ffortune500%2F2001%2Fcostco-wholesale-corporation-45%2F","encoded_shortlink":"http%3A%2F%2Fwp.me%2Fp4kUAt-1wrq","twitter_text":"Costco Wholesale Corporation on the Fortune 500 2001","facebook_desc":"","facebook_title":"Costco Wholesale Corporation - Fortune 500 2001 - Fortune","encoded_title":"Costco+Wholesale+Corporation+-+Fortune+500+2001+-+Fortune"}},{"id":363037,"post_type":"franchise-list-item","url":"\/fortune500\/2001\/safeway-inc-46\/","title":"Safeway Inc.","list_title":"Fortune 500 2001","content":"","rank":"46","thumbnail":"","featured_image":"","tables":"","buttons":"","ticker":"\u003Ctable class=\u0022tickershortcode company-market-data trend-wrapper unprocessed neutral\u0022 data-symbol=\u0022swy\u0022\u003E\n\t\t\t\t\u003Ctr\u003E\n\t\t\t\t\t\u003Ctd\u003E\u003Cspan class=\u0022ticker\u0022\u003ESWY\u003C\/span\u003E\u003C\/td\u003E\n\t\t\t\t\t\u003Ctd\u003E\u003Cspan class=\u0022tickerdata last\u0022\u003E\u003C\/span\u003E\u003Cspan class=\u0022change long\u0022\u003E\u003C\/span\u003E\u003C\/td\u003E\n\t\t\t\t\t\u003Ctd\u003E\u003Ctime class=\u0022tickerdata time\u0022\u003E\u003C\/time\u003E\u003C\/td\u003E\n\t\t\t\t\u003C\/tr\u003E\n\t\t\t\u003C\/table\u003E","ticker_text":"swy","highlights":{"Rank":"46","Previous Rank":"40","CEO":"Steven A. Burd","Address":"420 Montgomery St., San Francisco, CA 94163","Website":"www.safeway.com"},"linkedin":"","footnotes":"","ordering":"","year":"2001","franchise_name":"Fortune 500","right_rail_layout":"default","seo":{"seo_title":"Safeway Inc. - Fortune 500 2001 - Fortune","seo_description":"","seo_keywords":"","seo_news_keywords":"","seo_additional_meta":""},"social":{"encoded_url":"http%3A%2F%2Ffortune.com%2Ffortune500%2F2001%2Fsafeway-inc-46%2F","encoded_shortlink":"http%3A%2F%2Fwp.me%2Fp4kUAt-1wrr","twitter_text":"Safeway Inc. on the Fortune 500 2001","facebook_desc":"","facebook_title":"Safeway Inc. - Fortune 500 2001 - Fortune","encoded_title":"Safeway+Inc.+-+Fortune+500+2001+-+Fortune"}},{"id":363038,"post_type":"franchise-list-item","url":"\/fortune500\/2001\/metlife-inc-47\/","title":"MetLife Inc.","list_title":"Fortune 500 2001","content":"","rank":"47","thumbnail":"","featured_image":"","tables":"","buttons":"","ticker":"\u003Ctable class=\u0022tickershortcode company-market-data trend-wrapper unprocessed neutral\u0022 data-symbol=\u0022met\u0022\u003E\n\t\t\t\t\u003Ctr\u003E\n\t\t\t\t\t\u003Ctd\u003E\u003Cspan class=\u0022ticker\u0022\u003EMET\u003C\/span\u003E\u003C\/td\u003E\n\t\t\t\t\t\u003Ctd\u003E\u003Cspan class=\u0022tickerdata last\u0022\u003E\u003C\/span\u003E\u003Cspan class=\u0022change long\u0022\u003E\u003C\/span\u003E\u003C\/td\u003E\n\t\t\t\t\t\u003Ctd\u003E\u003Ctime class=\u0022tickerdata time\u0022\u003E\u003C\/time\u003E\u003C\/td\u003E\n\t\t\t\t\u003C\/tr\u003E\n\t\t\t\u003C\/table\u003E","ticker_text":"met","highlights":{"Rank":"47","Previous Rank":"53","CEO":"Robert H. Benmosche","Address":"1 Microsoft Way, Redmond, WA 98052","Website":"www.metlife.com"},"linkedin":"","footnotes":"","ordering":"","year":"2001","franchise_name":"Fortune 500","right_rail_layout":"default","seo":{"seo_title":"MetLife Inc. - Fortune 500 2001 - Fortune","seo_description":"","seo_keywords":"","seo_news_keywords":"","seo_additional_meta":""},"social":{"encoded_url":"http%3A%2F%2Ffortune.com%2Ffortune500%2F2001%2Fmetlife-inc-47%2F","encoded_shortlink":"http%3A%2F%2Fwp.me%2Fp4kUAt-1wrs","twitter_text":"MetLife Inc. on the Fortune 500 2001","facebook_desc":"","facebook_title":"MetLife Inc. - Fortune 500 2001 - Fortune","encoded_title":"MetLife+Inc.+-+Fortune+500+2001+-+Fortune"}},{"id":363039,"post_type":"franchise-list-item","url":"\/fortune500\/2001\/dell-computer-corporation-48\/","title":"Dell Computer Corporation","list_title":"Fortune 500 2001","content":"","rank":"48","thumbnail":"","featured_image":"","tables":"","buttons":"","ticker":"\u003Ctable class=\u0022tickershortcode company-market-data trend-wrapper unprocessed neutral\u0022 data-symbol=\u0022dell\u0022\u003E\n\t\t\t\t\u003Ctr\u003E\n\t\t\t\t\t\u003Ctd\u003E\u003Cspan class=\u0022ticker\u0022\u003EDELL\u003C\/span\u003E\u003C\/td\u003E\n\t\t\t\t\t\u003Ctd\u003E\u003Cspan class=\u0022tickerdata last\u0022\u003E\u003C\/span\u003E\u003Cspan class=\u0022change long\u0022\u003E\u003C\/span\u003E\u003C\/td\u003E\n\t\t\t\t\t\u003Ctd\u003E\u003Ctime class=\u0022tickerdata time\u0022\u003E\u003C\/time\u003E\u003C\/td\u003E\n\t\t\t\t\u003C\/tr\u003E\n\t\t\t\u003C\/table\u003E","ticker_text":"dell","highlights":{"Rank":"48","Previous Rank":"56","CEO":"Michael S. Dell","Address":"4 World Financial Center, New York, NY 10080","Website":"www.dell.com"},"linkedin":"","footnotes":"","ordering":"","year":"2001","franchise_name":"Fortune 500","right_rail_layout":"default","seo":{"seo_title":"Dell Computer Corporation - Fortune 500 2001 - Fortune","seo_description":"","seo_keywords":"","seo_news_keywords":"","seo_additional_meta":""},"social":{"encoded_url":"http%3A%2F%2Ffortune.com%2Ffortune500%2F2001%2Fdell-computer-corporation-48%2F","encoded_shortlink":"http%3A%2F%2Fwp.me%2Fp4kUAt-1wrt","twitter_text":"Dell Computer Corporation on the Fortune 500 2001","facebook_desc":"","facebook_title":"Dell Computer Corporation - Fortune 500 2001 - Fortune","encoded_title":"Dell+Computer+Corporation+-+Fortune+500+2001+-+Fortune"}},{"id":363040,"post_type":"franchise-list-item","url":"\/fortune500\/2001\/ingram-micro-inc-49\/","title":"Ingram Micro, Inc.","list_title":"Fortune 500 2001","content":"","rank":"49","thumbnail":"","featured_image":"","tables":"","buttons":"","ticker":"\u003Ctable class=\u0022tickershortcode company-market-data trend-wrapper unprocessed neutral\u0022 data-symbol=\u0022im\u0022\u003E\n\t\t\t\t\u003Ctr\u003E\n\t\t\t\t\t\u003Ctd\u003E\u003Cspan class=\u0022ticker\u0022\u003EIM\u003C\/span\u003E\u003C\/td\u003E\n\t\t\t\t\t\u003Ctd\u003E\u003Cspan class=\u0022tickerdata last\u0022\u003E\u003C\/span\u003E\u003Cspan class=\u0022change long\u0022\u003E\u003C\/span\u003E\u003C\/td\u003E\n\t\t\t\t\t\u003Ctd\u003E\u003Ctime class=\u0022tickerdata time\u0022\u003E\u003C\/time\u003E\u003C\/td\u003E\n\t\t\t\t\u003C\/tr\u003E\n\t\t\t\u003C\/table\u003E","ticker_text":"im","highlights":{"Rank":"49","Previous Rank":"41","CEO":"Kent B. Foster","Address":"1 Financial Plaza, Hartford, CT 6103","Website":"www.ingrammicro.com"},"linkedin":"","footnotes":"","ordering":"","year":"2001","franchise_name":"Fortune 500","right_rail_layout":"default","seo":{"seo_title":"Ingram Micro, Inc. - Fortune 500 2001 - Fortune","seo_description":"","seo_keywords":"","seo_news_keywords":"","seo_additional_meta":""},"social":{"encoded_url":"http%3A%2F%2Ffortune.com%2Ffortune500%2F2001%2Fingram-micro-inc-49%2F","encoded_shortlink":"http%3A%2F%2Fwp.me%2Fp4kUAt-1wru","twitter_text":"Ingram Micro, Inc. on the Fortune 500 2001","facebook_desc":"","facebook_title":"Ingram Micro, Inc. - Fortune 500 2001 - Fortune","encoded_title":"Ingram+Micro%2C+Inc.+-+Fortune+500+2001+-+Fortune"}},{"id":363041,"post_type":"franchise-list-item","url":"\/fortune500\/2001\/freddie-mac-50\/","title":"Freddie Mac","list_title":"Fortune 500 2001","content":"","rank":"50","thumbnail":"","featured_image":"","tables":"","buttons":"","ticker":"\u003Ctable class=\u0022tickershortcode company-market-data trend-wrapper unprocessed neutral\u0022 data-symbol=\u0022fre\u0022\u003E\n\t\t\t\t\u003Ctr\u003E\n\t\t\t\t\t\u003Ctd\u003E\u003Cspan class=\u0022ticker\u0022\u003EFRE\u003C\/span\u003E\u003C\/td\u003E\n\t\t\t\t\t\u003Ctd\u003E\u003Cspan class=\u0022tickerdata last\u0022\u003E\u003C\/span\u003E\u003Cspan class=\u0022change long\u0022\u003E\u003C\/span\u003E\u003C\/td\u003E\n\t\t\t\t\t\u003Ctd\u003E\u003Ctime class=\u0022tickerdata time\u0022\u003E\u003C\/time\u003E\u003C\/td\u003E\n\t\t\t\t\u003C\/tr\u003E\n\t\t\t\u003C\/table\u003E","ticker_text":"fre","highlights":{"Rank":"50","Previous Rank":"62","CEO":"Leland C. Brendsel","Address":"1 ConAgra Dr., Omaha, NE 68102","Website":"www.freddiemac.com"},"linkedin":"","footnotes":"","ordering":"","year":"2001","franchise_name":"Fortune 500","right_rail_layout":"default","seo":{"seo_title":"Freddie Mac - Fortune 500 2001 - Fortune","seo_description":"","seo_keywords":"","seo_news_keywords":"","seo_additional_meta":""},"social":{"encoded_url":"http%3A%2F%2Ffortune.com%2Ffortune500%2F2001%2Ffreddie-mac-50%2F","encoded_shortlink":"http%3A%2F%2Fwp.me%2Fp4kUAt-1wrv","twitter_text":"Freddie Mac on the Fortune 500 2001","facebook_desc":"","facebook_title":"Freddie Mac - Fortune 500 2001 - Fortune","encoded_title":"Freddie+Mac+-+Fortune+500+2001+-+Fortune"}},{"id":363042,"post_type":"franchise-list-item","url":"\/fortune500\/2001\/cardinal-health-inc-51\/","title":"Cardinal Health, Inc.","list_title":"Fortune 500 2001","content":"","rank":"51","thumbnail":"","featured_image":"","tables":"","buttons":"","ticker":"\u003Ctable class=\u0022tickershortcode company-market-data trend-wrapper unprocessed neutral\u0022 data-symbol=\u0022cah\u0022\u003E\n\t\t\t\t\u003Ctr\u003E\n\t\t\t\t\t\u003Ctd\u003E\u003Cspan class=\u0022ticker\u0022\u003ECAH\u003C\/span\u003E\u003C\/td\u003E\n\t\t\t\t\t\u003Ctd\u003E\u003Cspan class=\u0022tickerdata last\u0022\u003E\u003C\/span\u003E\u003Cspan class=\u0022change long\u0022\u003E\u003C\/span\u003E\u003C\/td\u003E\n\t\t\t\t\t\u003Ctd\u003E\u003Ctime class=\u0022tickerdata time\u0022\u003E\u003C\/time\u003E\u003C\/td\u003E\n\t\t\t\t\u003C\/tr\u003E\n\t\t\t\u003C\/table\u003E","ticker_text":"cah","highlights":{"Rank":"51","Previous Rank":"59","CEO":"Robert D. Walter","Address":"2030 Dow Center, Midland, MI 48674","Website":"www.cardinal.com"},"linkedin":"","footnotes":"","ordering":"","year":"2001","franchise_name":"Fortune 500","right_rail_layout":"default","seo":{"seo_title":"Cardinal Health, Inc. - Fortune 500 2001 - Fortune","seo_description":"","seo_keywords":"","seo_news_keywords":"","seo_additional_meta":""},"social":{"encoded_url":"http%3A%2F%2Ffortune.com%2Ffortune500%2F2001%2Fcardinal-health-inc-51%2F","encoded_shortlink":"http%3A%2F%2Fwp.me%2Fp4kUAt-1wrw","twitter_text":"Cardinal Health, Inc. on the Fortune 500 2001","facebook_desc":"","facebook_title":"Cardinal Health, Inc. - Fortune 500 2001 - Fortune","encoded_title":"Cardinal+Health%2C+Inc.+-+Fortune+500+2001+-+Fortune"}},{"id":363043,"post_type":"franchise-list-item","url":"\/fortune500\/2001\/united-parcel-service-of-america-inc-52\/","title":"United Parcel Service of America, Inc.","list_title":"Fortune 500 2001","content":"","rank":"52","thumbnail":"","featured_image":"","tables":"","buttons":"","ticker":"\u003Ctable class=\u0022tickershortcode company-market-data trend-wrapper unprocessed neutral\u0022 data-symbol=\u0022ups\u0022\u003E\n\t\t\t\t\u003Ctr\u003E\n\t\t\t\t\t\u003Ctd\u003E\u003Cspan class=\u0022ticker\u0022\u003EUPS\u003C\/span\u003E\u003C\/td\u003E\n\t\t\t\t\t\u003Ctd\u003E\u003Cspan class=\u0022tickerdata last\u0022\u003E\u003C\/span\u003E\u003Cspan class=\u0022change long\u0022\u003E\u003C\/span\u003E\u003C\/td\u003E\n\t\t\t\t\t\u003Ctd\u003E\u003Ctime class=\u0022tickerdata time\u0022\u003E\u003C\/time\u003E\u003C\/td\u003E\n\t\t\t\t\u003C\/tr\u003E\n\t\t\t\u003C\/table\u003E","ticker_text":"ups","highlights":{"Rank":"52","Previous Rank":"46","CEO":"James P. Kelly","Address":"5555 San Felipe Ave., Houston, TX 77056","Website":"www.ups.com"},"linkedin":"","footnotes":"","ordering":"","year":"2001","franchise_name":"Fortune 500","right_rail_layout":"default","seo":{"seo_title":"United Parcel Service of America, Inc. - Fortune 500 2001 - Fortune","seo_description":"","seo_keywords":"","seo_news_keywords":"","seo_additional_meta":""},"social":{"encoded_url":"http%3A%2F%2Ffortune.com%2Ffortune500%2F2001%2Funited-parcel-service-of-america-inc-52%2F","encoded_shortlink":"http%3A%2F%2Fwp.me%2Fp4kUAt-1wrx","twitter_text":"United Parcel Service of America, Inc. on the Fortune 500 2001","facebook_desc":"","facebook_title":"United Parcel Service of America, Inc. - Fortune 500 2001 - Fortune","encoded_title":"United+Parcel+Service+of+America%2C+Inc.+-+Fortune+500+2001+-+Fortune"}},{"id":363044,"post_type":"franchise-list-item","url":"\/fortune500\/2001\/pfizer-inc-53\/","title":"Pfizer Inc.","list_title":"Fortune 500 2001","content":"","rank":"53","thumbnail":"","featured_image":"","tables":"","buttons":"","ticker":"\u003Ctable class=\u0022tickershortcode company-market-data trend-wrapper unprocessed neutral\u0022 data-symbol=\u0022pfe\u0022\u003E\n\t\t\t\t\u003Ctr\u003E\n\t\t\t\t\t\u003Ctd\u003E\u003Cspan class=\u0022ticker\u0022\u003EPFE\u003C\/span\u003E\u003C\/td\u003E\n\t\t\t\t\t\u003Ctd\u003E\u003Cspan class=\u0022tickerdata last\u0022\u003E\u003C\/span\u003E\u003Cspan class=\u0022change long\u0022\u003E\u003C\/span\u003E\u003C\/td\u003E\n\t\t\t\t\t\u003Ctd\u003E\u003Ctime class=\u0022tickerdata time\u0022\u003E\u003C\/time\u003E\u003C\/td\u003E\n\t\t\t\t\u003C\/tr\u003E\n\t\t\t\u003C\/table\u003E","ticker_text":"pfe","highlights":{"Rank":"53","Previous Rank":"107","CEO":"Henry A. McKinnell","Address":"5725 Delphi Dr., Troy, MI 48098","Website":"www.pfizer.com"},"linkedin":"","footnotes":"","ordering":"","year":"2001","franchise_name":"Fortune 500","right_rail_layout":"default","seo":{"seo_title":"Pfizer Inc. - Fortune 500 2001 - Fortune","seo_description":"","seo_keywords":"","seo_news_keywords":"","seo_additional_meta":""},"social":{"encoded_url":"http%3A%2F%2Ffortune.com%2Ffortune500%2F2001%2Fpfizer-inc-53%2F","encoded_shortlink":"http%3A%2F%2Fwp.me%2Fp4kUAt-1wry","twitter_text":"Pfizer Inc. on the Fortune 500 2001","facebook_desc":"","facebook_title":"Pfizer Inc. - Fortune 500 2001 - Fortune","encoded_title":"Pfizer+Inc.+-+Fortune+500+2001+-+Fortune"}},{"id":363045,"post_type":"franchise-list-item","url":"\/fortune500\/2001\/dynegy-inc-54\/","title":"Dynegy Inc.","list_title":"Fortune 500 2001","content":"","rank":"54","thumbnail":"","featured_image":"","tables":"","buttons":"","ticker":"\u003Ctable class=\u0022tickershortcode company-market-data trend-wrapper unprocessed neutral\u0022 data-symbol=\u0022dyn\u0022\u003E\n\t\t\t\t\u003Ctr\u003E\n\t\t\t\t\t\u003Ctd\u003E\u003Cspan class=\u0022ticker\u0022\u003EDYN\u003C\/span\u003E\u003C\/td\u003E\n\t\t\t\t\t\u003Ctd\u003E\u003Cspan class=\u0022tickerdata last\u0022\u003E\u003C\/span\u003E\u003Cspan class=\u0022change long\u0022\u003E\u003C\/span\u003E\u003C\/td\u003E\n\t\t\t\t\t\u003Ctd\u003E\u003Ctime class=\u0022tickerdata time\u0022\u003E\u003C\/time\u003E\u003C\/td\u003E\n\t\t\t\t\u003C\/tr\u003E\n\t\t\t\u003C\/table\u003E","ticker_text":"dyn","highlights":{"Rank":"54","Previous Rank":"112","CEO":"Charles L. Watson","Address":"6200 Sprint Pkwy., Overland Park, KS 66214","Website":"www.dynegy.com"},"linkedin":"","footnotes":"","ordering":"","year":"2001","franchise_name":"Fortune 500","right_rail_layout":"default","seo":{"seo_title":"Dynegy Inc. - Fortune 500 2001 - Fortune","seo_description":"","seo_keywords":"","seo_news_keywords":"","seo_additional_meta":""},"social":{"encoded_url":"http%3A%2F%2Ffortune.com%2Ffortune500%2F2001%2Fdynegy-inc-54%2F","encoded_shortlink":"http%3A%2F%2Fwp.me%2Fp4kUAt-1wrz","twitter_text":"Dynegy Inc. on the Fortune 500 2001","facebook_desc":"","facebook_title":"Dynegy Inc. - Fortune 500 2001 - Fortune","encoded_title":"Dynegy+Inc.+-+Fortune+500+2001+-+Fortune"}},{"id":363046,"post_type":"franchise-list-item","url":"\/fortune500\/2001\/reliant-energy-incorporated-55\/","title":"Reliant Energy, Incorporated","list_title":"Fortune 500 2001","content":"","rank":"55","thumbnail":"","featured_image":"","tables":"","buttons":"","ticker":"\u003Ctable class=\u0022tickershortcode company-market-data trend-wrapper unprocessed neutral\u0022 data-symbol=\u0022rei\u0022\u003E\n\t\t\t\t\u003Ctr\u003E\n\t\t\t\t\t\u003Ctd\u003E\u003Cspan class=\u0022ticker\u0022\u003EREI\u003C\/span\u003E\u003C\/td\u003E\n\t\t\t\t\t\u003Ctd\u003E\u003Cspan class=\u0022tickerdata last\u0022\u003E\u003C\/span\u003E\u003Cspan class=\u0022change long\u0022\u003E\u003C\/span\u003E\u003C\/td\u003E\n\t\t\t\t\t\u003Ctd\u003E\u003Ctime class=\u0022tickerdata time\u0022\u003E\u003C\/time\u003E\u003C\/td\u003E\n\t\t\t\t\u003C\/tr\u003E\n\t\t\t\u003C\/table\u003E","ticker_text":"rei","highlights":{"Rank":"55","Previous Rank":"114","CEO":"R. Steve Letbetter","Address":"1 Valero Place, San Antonio, TX 78212","Website":"www.centerpointenergy.com"},"linkedin":"","footnotes":"","ordering":"","year":"2001","franchise_name":"Fortune 500","right_rail_layout":"default","seo":{"seo_title":"Reliant Energy, Incorporated - Fortune 500 2001 - Fortune","seo_description":"","seo_keywords":"","seo_news_keywords":"","seo_additional_meta":""},"social":{"encoded_url":"http%3A%2F%2Ffortune.com%2Ffortune500%2F2001%2Freliant-energy-incorporated-55%2F","encoded_shortlink":"http%3A%2F%2Fwp.me%2Fp4kUAt-1wrA","twitter_text":"Reliant Energy, Incorporated on the Fortune 500 2001","facebook_desc":"","facebook_title":"Reliant Energy, Incorporated - Fortune 500 2001 - Fortune","encoded_title":"Reliant+Energy%2C+Incorporated+-+Fortune+500+2001+-+Fortune"}},{"id":363047,"post_type":"franchise-list-item","url":"\/fortune500\/2001\/e-i-du-pont-de-nemours-and-company-inc-56\/","title":"E.I. du Pont de Nemours and Company, Inc.","list_title":"Fortune 500 2001","content":"","rank":"56","thumbnail":"","featured_image":"","tables":"","buttons":"","ticker":"\u003Ctable class=\u0022tickershortcode company-market-data trend-wrapper unprocessed neutral\u0022 data-symbol=\u0022dd\u0022\u003E\n\t\t\t\t\u003Ctr\u003E\n\t\t\t\t\t\u003Ctd\u003E\u003Cspan class=\u0022ticker\u0022\u003EDD\u003C\/span\u003E\u003C\/td\u003E\n\t\t\t\t\t\u003Ctd\u003E\u003Cspan class=\u0022tickerdata last\u0022\u003E\u003C\/span\u003E\u003Cspan class=\u0022change long\u0022\u003E\u003C\/span\u003E\u003C\/td\u003E\n\t\t\t\t\t\u003Ctd\u003E\u003Ctime class=\u0022tickerdata time\u0022\u003E\u003C\/time\u003E\u003C\/td\u003E\n\t\t\t\t\u003C\/tr\u003E\n\t\t\t\u003C\/table\u003E","ticker_text":"dd","highlights":{"Rank":"56","Previous Rank":"42","CEO":"Charles O. Holliday Jr.","Address":"6801 Rockledge Dr., Bethesda, MD 20817","Website":"www.dupont.com"},"linkedin":"","footnotes":"","ordering":"","year":"2001","franchise_name":"Fortune 500","right_rail_layout":"default","seo":{"seo_title":"E.I. du Pont de Nemours and Company, Inc. - Fortune 500 2001 - Fortune","seo_description":"","seo_keywords":"","seo_news_keywords":"","seo_additional_meta":""},"social":{"encoded_url":"http%3A%2F%2Ffortune.com%2Ffortune500%2F2001%2Fe-i-du-pont-de-nemours-and-company-inc-56%2F","encoded_shortlink":"http%3A%2F%2Fwp.me%2Fp4kUAt-1wrB","twitter_text":"E.I. du Pont de Nemours and Company, Inc. on the Fortune 500 2001","facebook_desc":"","facebook_title":"E.I. du Pont de Nemours and Company, Inc. - Fortune 500 2001 - Fortune","encoded_title":"E.I.+du+Pont+de+Nemours+and+Company%2C+Inc.+-+Fortune+500+2001+-+Fortune"}},{"id":363048,"post_type":"franchise-list-item","url":"\/fortune500\/2001\/delphi-automotive-systems-corporation-57\/","title":"Delphi Automotive Systems Corporation","list_title":"Fortune 500 2001","content":"","rank":"57","thumbnail":"","featured_image":"","tables":"","buttons":"","ticker":"\u003Ctable class=\u0022tickershortcode company-market-data trend-wrapper unprocessed neutral\u0022 data-symbol=\u0022dph\u0022\u003E\n\t\t\t\t\u003Ctr\u003E\n\t\t\t\t\t\u003Ctd\u003E\u003Cspan class=\u0022ticker\u0022\u003EDPH\u003C\/span\u003E\u003C\/td\u003E\n\t\t\t\t\t\u003Ctd\u003E\u003Cspan class=\u0022tickerdata last\u0022\u003E\u003C\/span\u003E\u003Cspan class=\u0022change long\u0022\u003E\u003C\/span\u003E\u003C\/td\u003E\n\t\t\t\t\t\u003Ctd\u003E\u003Ctime class=\u0022tickerdata time\u0022\u003E\u003C\/time\u003E\u003C\/td\u003E\n\t\t\t\t\u003C\/tr\u003E\n\t\t\t\u003C\/table\u003E","ticker_text":"dph","highlights":{"Rank":"57","Previous Rank":"-","CEO":"J. T. Battenberg III","Address":"751 Broad St., Newark, NJ 7102","Website":"www.delphi.com"},"linkedin":"","footnotes":"","ordering":"","year":"2001","franchise_name":"Fortune 500","right_rail_layout":"default","seo":{"seo_title":"Delphi Automotive Systems Corporation - Fortune 500 2001 - Fortune","seo_description":"","seo_keywords":"","seo_news_keywords":"","seo_additional_meta":""},"social":{"encoded_url":"http%3A%2F%2Ffortune.com%2Ffortune500%2F2001%2Fdelphi-automotive-systems-corporation-57%2F","encoded_shortlink":"http%3A%2F%2Fwp.me%2Fp4kUAt-1wrC","twitter_text":"Delphi Automotive Systems Corporation on the Fortune 500 2001","facebook_desc":"","facebook_title":"Delphi Automotive Systems Corporation - Fortune 500 2001 - Fortune","encoded_title":"Delphi+Automotive+Systems+Corporation+-+Fortune+500+2001+-+Fortune"}},{"id":363049,"post_type":"franchise-list-item","url":"\/fortune500\/2001\/johnson-johnson-57\/","title":"Johnson \u0026 Johnson","list_title":"Fortune 500 2001","content":"","rank":"57","thumbnail":"","featured_image":"","tables":"","buttons":"","ticker":"\u003Ctable class=\u0022tickershortcode company-market-data trend-wrapper unprocessed neutral\u0022 data-symbol=\u0022jnj\u0022\u003E\n\t\t\t\t\u003Ctr\u003E\n\t\t\t\t\t\u003Ctd\u003E\u003Cspan class=\u0022ticker\u0022\u003EJNJ\u003C\/span\u003E\u003C\/td\u003E\n\t\t\t\t\t\u003Ctd\u003E\u003Cspan class=\u0022tickerdata last\u0022\u003E\u003C\/span\u003E\u003Cspan class=\u0022change long\u0022\u003E\u003C\/span\u003E\u003C\/td\u003E\n\t\t\t\t\t\u003Ctd\u003E\u003Ctime class=\u0022tickerdata time\u0022\u003E\u003C\/time\u003E\u003C\/td\u003E\n\t\t\t\t\u003C\/tr\u003E\n\t\t\t\u003C\/table\u003E","ticker_text":"jnj","highlights":{"Rank":"57","Previous Rank":"43","CEO":"Ralph S. Larsen","Address":"2200 Mission College Blvd., Santa Clara, CA 95052","Website":"www.jnj.com"},"linkedin":"","footnotes":"","ordering":"","year":"2001","franchise_name":"Fortune 500","right_rail_layout":"default","seo":{"seo_title":"Johnson \u0026 Johnson - Fortune 500 2001 - Fortune","seo_description":"","seo_keywords":"","seo_news_keywords":"","seo_additional_meta":""},"social":{"encoded_url":"http%3A%2F%2Ffortune.com%2Ffortune500%2F2001%2Fjohnson-johnson-57%2F","encoded_shortlink":"http%3A%2F%2Fwp.me%2Fp4kUAt-1wrD","twitter_text":"Johnson \u0026 Johnson on the Fortune 500 2001","facebook_desc":"","facebook_title":"Johnson \u0026 Johnson - Fortune 500 2001 - Fortune","encoded_title":"Johnson+%26+Johnson+-+Fortune+500+2001+-+Fortune"}},{"id":363050,"post_type":"franchise-list-item","url":"\/fortune500\/2001\/the-allstate-corporation-59\/","title":"The Allstate Corporation","list_title":"Fortune 500 2001","content":"","rank":"59","thumbnail":"","featured_image":"","tables":"","buttons":"","ticker":"\u003Ctable class=\u0022tickershortcode company-market-data trend-wrapper unprocessed neutral\u0022 data-symbol=\u0022all\u0022\u003E\n\t\t\t\t\u003Ctr\u003E\n\t\t\t\t\t\u003Ctd\u003E\u003Cspan class=\u0022ticker\u0022\u003EALL\u003C\/span\u003E\u003C\/td\u003E\n\t\t\t\t\t\u003Ctd\u003E\u003Cspan class=\u0022tickerdata last\u0022\u003E\u003C\/span\u003E\u003Cspan class=\u0022change long\u0022\u003E\u003C\/span\u003E\u003C\/td\u003E\n\t\t\t\t\t\u003Ctd\u003E\u003Ctime class=\u0022tickerdata time\u0022\u003E\u003C\/time\u003E\u003C\/td\u003E\n\t\t\t\t\u003C\/tr\u003E\n\t\t\t\u003C\/table\u003E","ticker_text":"all","highlights":{"Rank":"59","Previous Rank":"47","CEO":"Edward M. Liddy","Address":"1303 E. Algonquin Rd., Schaumburg, IL 60196","Website":"www.allstate.com"},"linkedin":"","footnotes":"","ordering":"","year":"2001","franchise_name":"Fortune 500","right_rail_layout":"default","seo":{"seo_title":"The Allstate Corporation - Fortune 500 2001 - Fortune","seo_description":"","seo_keywords":"","seo_news_keywords":"","seo_additional_meta":""},"social":{"encoded_url":"http%3A%2F%2Ffortune.com%2Ffortune500%2F2001%2Fthe-allstate-corporation-59%2F","encoded_shortlink":"http%3A%2F%2Fwp.me%2Fp4kUAt-1wrE","twitter_text":"The Allstate Corporation on the Fortune 500 2001","facebook_desc":"","facebook_title":"The Allstate Corporation - Fortune 500 2001 - Fortune","encoded_title":"The+Allstate+Corporation+-+Fortune+500+2001+-+Fortune"}},{"id":363051,"post_type":"franchise-list-item","url":"\/fortune500\/2001\/utilicorp-united-inc-60\/","title":"UtiliCorp United Inc.","list_title":"Fortune 500 2001","content":"","rank":"60","thumbnail":"","featured_image":"","tables":"","buttons":"","ticker":"\u003Ctable class=\u0022tickershortcode company-market-data trend-wrapper unprocessed neutral\u0022 data-symbol=\u0022ucu\u0022\u003E\n\t\t\t\t\u003Ctr\u003E\n\t\t\t\t\t\u003Ctd\u003E\u003Cspan class=\u0022ticker\u0022\u003EUCU\u003C\/span\u003E\u003C\/td\u003E\n\t\t\t\t\t\u003Ctd\u003E\u003Cspan class=\u0022tickerdata last\u0022\u003E\u003C\/span\u003E\u003Cspan class=\u0022change long\u0022\u003E\u003C\/span\u003E\u003C\/td\u003E\n\t\t\t\t\t\u003Ctd\u003E\u003Ctime class=\u0022tickerdata time\u0022\u003E\u003C\/time\u003E\u003C\/td\u003E\n\t\t\t\t\u003C\/tr\u003E\n\t\t\t\u003C\/table\u003E","ticker_text":"ucu","highlights":{"Rank":"60","Previous Rank":"90","CEO":"Richard C. Green Jr.","Address":"1605 Curtis Bridge Rd., Wilkesboro, NC 28697","Website":"www.aquila.com"},"linkedin":"","footnotes":"","ordering":"","year":"2001","franchise_name":"Fortune 500","right_rail_layout":"default","seo":{"seo_title":"UtiliCorp United Inc. - Fortune 500 2001 - Fortune","seo_description":"","seo_keywords":"","seo_news_keywords":"","seo_additional_meta":""},"social":{"encoded_url":"http%3A%2F%2Ffortune.com%2Ffortune500%2F2001%2Futilicorp-united-inc-60%2F","encoded_shortlink":"http%3A%2F%2Fwp.me%2Fp4kUAt-1wrF","twitter_text":"UtiliCorp United Inc. on the Fortune 500 2001","facebook_desc":"","facebook_title":"UtiliCorp United Inc. - Fortune 500 2001 - Fortune","encoded_title":"UtiliCorp+United+Inc.+-+Fortune+500+2001+-+Fortune"}},{"id":363052,"post_type":"franchise-list-item","url":"\/fortune500\/2001\/international-paper-company-61\/","title":"International Paper Company","list_title":"Fortune 500 2001","content":"","rank":"61","thumbnail":"","featured_image":"","tables":"","buttons":"","ticker":"\u003Ctable class=\u0022tickershortcode company-market-data trend-wrapper unprocessed neutral\u0022 data-symbol=\u0022ip\u0022\u003E\n\t\t\t\t\u003Ctr\u003E\n\t\t\t\t\t\u003Ctd\u003E\u003Cspan class=\u0022ticker\u0022\u003EIP\u003C\/span\u003E\u003C\/td\u003E\n\t\t\t\t\t\u003Ctd\u003E\u003Cspan class=\u0022tickerdata last\u0022\u003E\u003C\/span\u003E\u003Cspan class=\u0022change long\u0022\u003E\u003C\/span\u003E\u003C\/td\u003E\n\t\t\t\t\t\u003Ctd\u003E\u003Ctime class=\u0022tickerdata time\u0022\u003E\u003C\/time\u003E\u003C\/td\u003E\n\t\t\t\t\u003C\/tr\u003E\n\t\t\t\u003C\/table\u003E","ticker_text":"ip","highlights":{"Rank":"61","Previous Rank":"61","CEO":"John T. Dillon","Address":"500 S. Buena Vista St., Burbank, CA 91521","Website":"www.internationalpaper.com"},"linkedin":"","footnotes":"","ordering":"","year":"2001","franchise_name":"Fortune 500","right_rail_layout":"default","seo":{"seo_title":"International Paper Company - Fortune 500 2001 - Fortune","seo_description":"","seo_keywords":"","seo_news_keywords":"","seo_additional_meta":""},"social":{"encoded_url":"http%3A%2F%2Ffortune.com%2Ffortune500%2F2001%2Finternational-paper-company-61%2F","encoded_shortlink":"http%3A%2F%2Fwp.me%2Fp4kUAt-1wrG","twitter_text":"International Paper Company on the Fortune 500 2001","facebook_desc":"","facebook_title":"International Paper Company - Fortune 500 2001 - Fortune","encoded_title":"International+Paper+Company+-+Fortune+500+2001+-+Fortune"}}]}