{"list":{"id":368005,"post_type":"franchise-list","post_title":"Fortune 500 1996","post_content":"","post_excerpt":"","year":"1996","short_name":"Fortune 500 1996","methodology":"","fortune_intro_title":"","top_stories":[],"franchise_type":"","filters":{"Industry":{"51":"Advertising, marketing","27":"Aerospace","32":"Airlines","42":"Apparel","54":"Automotive Retailing, Services","41":"Beverages","45":"Building Materials, Glass","5":"Chemicals","2":"Commercial Banks","24":"Computer And Data Services","15":"Computers, Office Equipment","25":"Diversified Financials","4":"Electronics, Electrical Equip.","23":"Engineering, Construction","50":"Entertainment","7":"Food","6":"Food and Drug Stores","28":"Food Services","8":"Forest and Paper Products","49":"Furniture","18":"General Merchandisers","10":"Health Care","38":"Hotels, Casinos, Resorts","9":"Industrial and Farm Equipment","12":"Insurance: Life, Health (Mutual)","20":"Insurance: Life, Health (stock)","34":"Insurance: Property and Casualty (Mutual)","11":"Insurance: Property and Casualty (Stock)","48":"Mail, Package, and Freight Delivery","55":"Marine services","22":"Metal Products","17":"Metals","40":"Mining, Crude-Oil Production","14":"Motor Vehicles and Parts","13":"Petroleum Refining","26":"Pharmaceuticals","31":"Pipelines","21":"Publishing, Printing","44":"Railroads","30":"Rubber and Plastic Products","37":"Savings Institutions","19":"Scientific,Photographic and Control Equipment","33":"Soaps, Cosmetics","3":"Specialty Retailers","16":"Telecommunications","47":"Temporary Help","29":"Textiles","43":"Tobacco","53":"Toys, Sporting Goods","46":"Transportation Equipment","36":"Trucking","0":"Utilities: Gas and Electric","52":"Waste Management","1":"Wholesalers","39":"X Brokerage","35":"zMiscellaneous"},"Headquarters State":{"20":"AL","25":"AR","28":"AZ","1":"CA","23":"CO","6":"CT","24":"DC","27":"DE","14":"FL","12":"GA","41":"HI","33":"IA","36":"ID","2":"IL","17":"IN","35":"KS","31":"KY","34":"LA","7":"MA","19":"MD","40":"ME","9":"MI","10":"MN","11":"MO","48":"MS","47":"MT","16":"NC","30":"NE","39":"NH","8":"NJ","46":"NM","38":"NV","0":"NY","3":"OH","26":"OK","22":"OR","5":"PA","45":"PR","37":"RI","29":"SC","44":"SD","18":"TN","4":"TX","32":"UT","13":"VA","43":"VT","21":"WA","15":"WI","42":"WV"}},"sort":["Rank","Revenues"],"translations":{"Headquarters State":{"AL":"Alabama","AK":"Alaska","AZ":"Arizona","AR":"Arkansas","CA":"California","CO":"Colorado","CT":"Connecticut","DE":"Delaware","DC":"District Of Columbia","FL":"Florida","GA":"Georgia","HI":"Hawaii","ID":"Idaho","IL":"Illinois","IN":"Indiana","IA":"Iowa","KS":"Kansas","KY":"Kentucky","LA":"Louisiana","ME":"Maine","MD":"Maryland","MA":"Massachusetts","MI":"Michigan","MN":"Minnesota","MS":"Mississippi","MO":"Missouri","MT":"Montana","NE":"Nebraska","NV":"Nevada","NH":"New Hampshire","NJ":"New Jersey","NM":"New Mexico","NY":"New York","NC":"North Carolina","ND":"North Dakota","OH":"Ohio","OK":"Oklahoma","OR":"Oregon","PA":"Pennsylvania","PR":"Puerto Rico","RI":"Rhode Island","SC":"South Carolina","SD":"South Dakota","TN":"Tennessee","TX":"Texas","UT":"Utah","VT":"Vermont","VA":"Virginia","WA":"Washington","WV":"West Virginia","WI":"Wisconsin","WY":"Wyoming"}},"social":{"encoded_url":"http%3A%2F%2Ffortune.com%2Ffortune500%2F1996%2F","encoded_shortlink":"http%3A%2F%2Fwp.me%2Fp4kUAt-1xJz","twitter_text":"Fortune 500 1996","encoded_title":"Fortune+500+1996"}},"articles":[{"id":368057,"post_type":"franchise-list-item","url":"\/fortune500\/1996\/pepsico-inc-21\/","title":"PepsiCo, Inc.","list_title":"Fortune 500 1996","content":"","rank":"21","thumbnail":"","featured_image":"","tables":"","buttons":"","ticker":"\u003Ctable class=\u0022tickershortcode company-market-data trend-wrapper unprocessed neutral\u0022 data-symbol=\u0022pep\u0022\u003E\n\t\t\t\t\u003Ctr\u003E\n\t\t\t\t\t\u003Ctd\u003E\u003Cspan class=\u0022ticker\u0022\u003EPEP\u003C\/span\u003E\u003C\/td\u003E\n\t\t\t\t\t\u003Ctd\u003E\u003Cspan class=\u0022tickerdata last\u0022\u003E\u003C\/span\u003E\u003Cspan class=\u0022change long\u0022\u003E\u003C\/span\u003E\u003C\/td\u003E\n\t\t\t\t\t\u003Ctd\u003E\u003Ctime class=\u0022tickerdata time\u0022\u003E\u003C\/time\u003E\u003C\/td\u003E\n\t\t\t\t\u003C\/tr\u003E\n\t\t\t\u003C\/table\u003E","ticker_text":"pep","highlights":{"Rank":"21","Previous Rank":"20","CEO":"Roger Enrico","Address":"1 State Farm Plaza, Bloomington, IL 61710","Website":"www.pepsico.com"},"linkedin":"","footnotes":"","ordering":"","year":"1996","franchise_name":"Fortune 500","right_rail_layout":"default","seo":{"seo_title":"PepsiCo, Inc. - Fortune 500 1996 - Fortune","seo_description":"","seo_keywords":"","seo_news_keywords":"","seo_additional_meta":""},"social":{"encoded_url":"http%3A%2F%2Ffortune.com%2Ffortune500%2F1996%2Fpepsico-inc-21%2F","encoded_shortlink":"http%3A%2F%2Fwp.me%2Fp4kUAt-1xKp","twitter_text":"PepsiCo, Inc. on the Fortune 500 1996","facebook_desc":"","facebook_title":"PepsiCo, Inc. - Fortune 500 1996 - Fortune","encoded_title":"PepsiCo%2C+Inc.+-+Fortune+500+1996+-+Fortune"}},{"id":368058,"post_type":"franchise-list-item","url":"\/fortune500\/1996\/metropolitan-life-insurance-co-22\/","title":"Metropolitan Life Insurance Co.","list_title":"Fortune 500 1996","content":"","rank":"22","thumbnail":"","featured_image":"","tables":"","buttons":"","ticker":"","ticker_text":"","highlights":{"Rank":"22","Previous Rank":"27","CEO":"Harry P. Kamen","Address":"1 AT\u0026T Way, Bedminster, NJ 7921","Website":"www.metlife.com"},"linkedin":"","footnotes":"","ordering":"","year":"1996","franchise_name":"Fortune 500","seo":{"seo_title":"Metropolitan Life Insurance Co. - Fortune 500 1996 - Fortune","seo_description":"","seo_keywords":"","seo_news_keywords":"","seo_additional_meta":""},"social":{"encoded_url":"http%3A%2F%2Ffortune.com%2Ffortune500%2F1996%2Fmetropolitan-life-insurance-co-22%2F","encoded_shortlink":"http%3A%2F%2Fwp.me%2Fp4kUAt-1xKq","twitter_text":"Metropolitan Life Insurance Co. on the Fortune 500 1996","facebook_desc":"","facebook_title":"Metropolitan Life Insurance Co. - Fortune 500 1996 - Fortune","encoded_title":"Metropolitan+Life+Insurance+Co.+-+Fortune+500+1996+-+Fortune"}},{"id":368059,"post_type":"franchise-list-item","url":"\/fortune500\/1996\/amoco-corporation-23\/","title":"Amoco Corporation","list_title":"Fortune 500 1996","content":"","rank":"23","thumbnail":"","featured_image":"","tables":"","buttons":"","ticker":"\u003Ctable class=\u0022tickershortcode company-market-data trend-wrapper unprocessed neutral\u0022 data-symbol=\u0022an\u0022\u003E\n\t\t\t\t\u003Ctr\u003E\n\t\t\t\t\t\u003Ctd\u003E\u003Cspan class=\u0022ticker\u0022\u003EAN\u003C\/span\u003E\u003C\/td\u003E\n\t\t\t\t\t\u003Ctd\u003E\u003Cspan class=\u0022tickerdata last\u0022\u003E\u003C\/span\u003E\u003Cspan class=\u0022change long\u0022\u003E\u003C\/span\u003E\u003C\/td\u003E\n\t\t\t\t\t\u003Ctd\u003E\u003Ctime class=\u0022tickerdata time\u0022\u003E\u003C\/time\u003E\u003C\/td\u003E\n\t\t\t\t\u003C\/tr\u003E\n\t\t\t\u003C\/table\u003E","ticker_text":"an","highlights":{"Rank":"23","Previous Rank":"21","CEO":"H. Laurance Fuller","Address":"100 N. Tryon St., Charlotte, NC 28255","Website":"www.amoco.com"},"linkedin":"","footnotes":"","ordering":"","year":"1996","franchise_name":"Fortune 500","right_rail_layout":"default","seo":{"seo_title":"Amoco Corporation - Fortune 500 1996 - Fortune","seo_description":"","seo_keywords":"","seo_news_keywords":"","seo_additional_meta":""},"social":{"encoded_url":"http%3A%2F%2Ffortune.com%2Ffortune500%2F1996%2Famoco-corporation-23%2F","encoded_shortlink":"http%3A%2F%2Fwp.me%2Fp4kUAt-1xKr","twitter_text":"Amoco Corporation on the Fortune 500 1996","facebook_desc":"","facebook_title":"Amoco Corporation - Fortune 500 1996 - Fortune","encoded_title":"Amoco+Corporation+-+Fortune+500+1996+-+Fortune"}},{"id":368060,"post_type":"franchise-list-item","url":"\/fortune500\/1996\/motorola-inc-24\/","title":"Motorola, Inc.","list_title":"Fortune 500 1996","content":"","rank":"24","thumbnail":"","featured_image":"","tables":"","buttons":"","ticker":"\u003Ctable class=\u0022tickershortcode company-market-data trend-wrapper unprocessed neutral\u0022 data-symbol=\u0022mot\u0022\u003E\n\t\t\t\t\u003Ctr\u003E\n\t\t\t\t\t\u003Ctd\u003E\u003Cspan class=\u0022ticker\u0022\u003EMOT\u003C\/span\u003E\u003C\/td\u003E\n\t\t\t\t\t\u003Ctd\u003E\u003Cspan class=\u0022tickerdata last\u0022\u003E\u003C\/span\u003E\u003Cspan class=\u0022change long\u0022\u003E\u003C\/span\u003E\u003C\/td\u003E\n\t\t\t\t\t\u003Ctd\u003E\u003Ctime class=\u0022tickerdata time\u0022\u003E\u003C\/time\u003E\u003C\/td\u003E\n\t\t\t\t\u003C\/tr\u003E\n\t\t\t\u003C\/table\u003E","ticker_text":"mot","highlights":{"Rank":"24","Previous Rank":"28","CEO":"Gary L. Tooker","Address":"1300 Morris Dr., Chesterbrook, PA 19087","Website":"www.motorolasolutions.com"},"linkedin":"","footnotes":"","ordering":"","year":"1996","franchise_name":"Fortune 500","right_rail_layout":"default","seo":{"seo_title":"Motorola, Inc. - Fortune 500 1996 - Fortune","seo_description":"","seo_keywords":"","seo_news_keywords":"","seo_additional_meta":""},"social":{"encoded_url":"http%3A%2F%2Ffortune.com%2Ffortune500%2F1996%2Fmotorola-inc-24%2F","encoded_shortlink":"http%3A%2F%2Fwp.me%2Fp4kUAt-1xKs","twitter_text":"Motorola, Inc. on the Fortune 500 1996","facebook_desc":"","facebook_title":"Motorola, Inc. - Fortune 500 1996 - Fortune","encoded_title":"Motorola%2C+Inc.+-+Fortune+500+1996+-+Fortune"}},{"id":368061,"post_type":"franchise-list-item","url":"\/fortune500\/1996\/american-international-groupinc-25\/","title":"American International Group,Inc.","list_title":"Fortune 500 1996","content":"","rank":"25","thumbnail":"","featured_image":"","tables":"","buttons":"","ticker":"\u003Ctable class=\u0022tickershortcode company-market-data trend-wrapper unprocessed neutral\u0022 data-symbol=\u0022aig\u0022\u003E\n\t\t\t\t\u003Ctr\u003E\n\t\t\t\t\t\u003Ctd\u003E\u003Cspan class=\u0022ticker\u0022\u003EAIG\u003C\/span\u003E\u003C\/td\u003E\n\t\t\t\t\t\u003Ctd\u003E\u003Cspan class=\u0022tickerdata last\u0022\u003E\u003C\/span\u003E\u003Cspan class=\u0022change long\u0022\u003E\u003C\/span\u003E\u003C\/td\u003E\n\t\t\t\t\t\u003Ctd\u003E\u003Ctime class=\u0022tickerdata time\u0022\u003E\u003C\/time\u003E\u003C\/td\u003E\n\t\t\t\t\u003C\/tr\u003E\n\t\t\t\u003C\/table\u003E","ticker_text":"aig","highlights":{"Rank":"25","Previous Rank":"26","CEO":"Maurice R. Greenberg","Address":"1000 Nicollet Mall, Minneapolis, MN 55403","Website":"www.aig.com"},"linkedin":"","footnotes":"","ordering":"","year":"1996","franchise_name":"Fortune 500","right_rail_layout":"default","seo":{"seo_title":"American International Group,Inc. - Fortune 500 1996 - Fortune","seo_description":"","seo_keywords":"","seo_news_keywords":"","seo_additional_meta":""},"social":{"encoded_url":"http%3A%2F%2Ffortune.com%2Ffortune500%2F1996%2Famerican-international-groupinc-25%2F","encoded_shortlink":"http%3A%2F%2Fwp.me%2Fp4kUAt-1xKt","twitter_text":"American International Group,Inc. on the Fortune 500 1996","facebook_desc":"","facebook_title":"American International Group,Inc. - Fortune 500 1996 - Fortune","encoded_title":"American+International+Group%2CInc.+-+Fortune+500+1996+-+Fortune"}},{"id":368062,"post_type":"franchise-list-item","url":"\/fortune500\/1996\/conagra-inc-26\/","title":"ConAgra, Inc.","list_title":"Fortune 500 1996","content":"","rank":"26","thumbnail":"","featured_image":"","tables":"","buttons":"","ticker":"\u003Ctable class=\u0022tickershortcode company-market-data trend-wrapper unprocessed neutral\u0022 data-symbol=\u0022cag\u0022\u003E\n\t\t\t\t\u003Ctr\u003E\n\t\t\t\t\t\u003Ctd\u003E\u003Cspan class=\u0022ticker\u0022\u003ECAG\u003C\/span\u003E\u003C\/td\u003E\n\t\t\t\t\t\u003Ctd\u003E\u003Cspan class=\u0022tickerdata last\u0022\u003E\u003C\/span\u003E\u003Cspan class=\u0022change long\u0022\u003E\u003C\/span\u003E\u003C\/td\u003E\n\t\t\t\t\t\u003Ctd\u003E\u003Ctime class=\u0022tickerdata time\u0022\u003E\u003C\/time\u003E\u003C\/td\u003E\n\t\t\t\t\u003C\/tr\u003E\n\t\t\t\u003C\/table\u003E","ticker_text":"cag","highlights":{"Rank":"26","Previous Rank":"24","CEO":"Philip B. Fletcher","Address":"270 Park Ave., New York, NY 10017","Website":"www.conagrafoods.com"},"linkedin":"","footnotes":"","ordering":"","year":"1996","franchise_name":"Fortune 500","right_rail_layout":"default","seo":{"seo_title":"ConAgra, Inc. - Fortune 500 1996 - Fortune","seo_description":"","seo_keywords":"","seo_news_keywords":"","seo_additional_meta":""},"social":{"encoded_url":"http%3A%2F%2Ffortune.com%2Ffortune500%2F1996%2Fconagra-inc-26%2F","encoded_shortlink":"http%3A%2F%2Fwp.me%2Fp4kUAt-1xKu","twitter_text":"ConAgra, Inc. on the Fortune 500 1996","facebook_desc":"","facebook_title":"ConAgra, Inc. - Fortune 500 1996 - Fortune","encoded_title":"ConAgra%2C+Inc.+-+Fortune+500+1996+-+Fortune"}},{"id":368063,"post_type":"franchise-list-item","url":"\/fortune500\/1996\/the-kroger-company-27\/","title":"The Kroger Company","list_title":"Fortune 500 1996","content":"","rank":"27","thumbnail":"","featured_image":"","tables":"","buttons":"","ticker":"\u003Ctable class=\u0022tickershortcode company-market-data trend-wrapper unprocessed neutral\u0022 data-symbol=\u0022kr\u0022\u003E\n\t\t\t\t\u003Ctr\u003E\n\t\t\t\t\t\u003Ctd\u003E\u003Cspan class=\u0022ticker\u0022\u003EKR\u003C\/span\u003E\u003C\/td\u003E\n\t\t\t\t\t\u003Ctd\u003E\u003Cspan class=\u0022tickerdata last\u0022\u003E\u003C\/span\u003E\u003Cspan class=\u0022change long\u0022\u003E\u003C\/span\u003E\u003C\/td\u003E\n\t\t\t\t\t\u003Ctd\u003E\u003Ctime class=\u0022tickerdata time\u0022\u003E\u003C\/time\u003E\u003C\/td\u003E\n\t\t\t\t\u003C\/tr\u003E\n\t\t\t\u003C\/table\u003E","ticker_text":"kr","highlights":{"Rank":"27","Previous Rank":"25","CEO":"Joseph A. Pichler","Address":"175 E. Houston St., San Antonio, TX 78205","Website":"www.thekrogerco.com"},"linkedin":"","footnotes":"","ordering":"","year":"1996","franchise_name":"Fortune 500","right_rail_layout":"default","seo":{"seo_title":"The Kroger Company - Fortune 500 1996 - Fortune","seo_description":"","seo_keywords":"","seo_news_keywords":"","seo_additional_meta":""},"social":{"encoded_url":"http%3A%2F%2Ffortune.com%2Ffortune500%2F1996%2Fthe-kroger-company-27%2F","encoded_shortlink":"http%3A%2F%2Fwp.me%2Fp4kUAt-1xKv","twitter_text":"The Kroger Company on the Fortune 500 1996","facebook_desc":"","facebook_title":"The Kroger Company - Fortune 500 1996 - Fortune","encoded_title":"The+Kroger+Company+-+Fortune+500+1996+-+Fortune"}},{"id":368064,"post_type":"franchise-list-item","url":"\/fortune500\/1996\/dayton-hudson-corporation-28\/","title":"Dayton Hudson Corporation","list_title":"Fortune 500 1996","content":"","rank":"28","thumbnail":"","featured_image":"","tables":"","buttons":"","ticker":"\u003Ctable class=\u0022tickershortcode company-market-data trend-wrapper unprocessed neutral\u0022 data-symbol=\u0022dh\u0022\u003E\n\t\t\t\t\u003Ctr\u003E\n\t\t\t\t\t\u003Ctd\u003E\u003Cspan class=\u0022ticker\u0022\u003EDH\u003C\/span\u003E\u003C\/td\u003E\n\t\t\t\t\t\u003Ctd\u003E\u003Cspan class=\u0022tickerdata last\u0022\u003E\u003C\/span\u003E\u003Cspan class=\u0022change long\u0022\u003E\u003C\/span\u003E\u003C\/td\u003E\n\t\t\t\t\t\u003Ctd\u003E\u003Ctime class=\u0022tickerdata time\u0022\u003E\u003C\/time\u003E\u003C\/td\u003E\n\t\t\t\t\u003C\/tr\u003E\n\t\t\t\u003C\/table\u003E","ticker_text":"dh","highlights":{"Rank":"28","Previous Rank":"30","CEO":"Robert J. Ulrich","Address":"1440 Kiewit Plaza, Omaha, NE 68131","Website":"www.target.com"},"linkedin":"","footnotes":"","ordering":"","year":"1996","franchise_name":"Fortune 500","right_rail_layout":"default","seo":{"seo_title":"Dayton Hudson Corporation - Fortune 500 1996 - Fortune","seo_description":"","seo_keywords":"","seo_news_keywords":"","seo_additional_meta":""},"social":{"encoded_url":"http%3A%2F%2Ffortune.com%2Ffortune500%2F1996%2Fdayton-hudson-corporation-28%2F","encoded_shortlink":"http%3A%2F%2Fwp.me%2Fp4kUAt-1xKw","twitter_text":"Dayton Hudson Corporation on the Fortune 500 1996","facebook_desc":"","facebook_title":"Dayton Hudson Corporation - Fortune 500 1996 - Fortune","encoded_title":"Dayton+Hudson+Corporation+-+Fortune+500+1996+-+Fortune"}},{"id":368065,"post_type":"franchise-list-item","url":"\/fortune500\/1996\/lockheed-martin-corporation-29\/","title":"Lockheed Martin Corporation","list_title":"Fortune 500 1996","content":"","rank":"29","thumbnail":"","featured_image":"","tables":"","buttons":"","ticker":"\u003Ctable class=\u0022tickershortcode company-market-data trend-wrapper unprocessed neutral\u0022 data-symbol=\u0022lmt\u0022\u003E\n\t\t\t\t\u003Ctr\u003E\n\t\t\t\t\t\u003Ctd\u003E\u003Cspan class=\u0022ticker\u0022\u003ELMT\u003C\/span\u003E\u003C\/td\u003E\n\t\t\t\t\t\u003Ctd\u003E\u003Cspan class=\u0022tickerdata last\u0022\u003E\u003C\/span\u003E\u003Cspan class=\u0022change long\u0022\u003E\u003C\/span\u003E\u003C\/td\u003E\n\t\t\t\t\t\u003Ctd\u003E\u003Ctime class=\u0022tickerdata time\u0022\u003E\u003C\/time\u003E\u003C\/td\u003E\n\t\t\t\t\u003C\/tr\u003E\n\t\t\t\u003C\/table\u003E","ticker_text":"lmt","highlights":{"Rank":"29","Previous Rank":"70","CEO":"Norman Augustine","Address":"75 Rockefeller Plaza, New York, NY 10019","Website":"www.lockheedmartin.com"},"linkedin":"","footnotes":"","ordering":"","year":"1996","franchise_name":"Fortune 500","right_rail_layout":"default","seo":{"seo_title":"Lockheed Martin Corporation - Fortune 500 1996 - Fortune","seo_description":"","seo_keywords":"","seo_news_keywords":"","seo_additional_meta":""},"social":{"encoded_url":"http%3A%2F%2Ffortune.com%2Ffortune500%2F1996%2Flockheed-martin-corporation-29%2F","encoded_shortlink":"http%3A%2F%2Fwp.me%2Fp4kUAt-1xKx","twitter_text":"Lockheed Martin Corporation on the Fortune 500 1996","facebook_desc":"","facebook_title":"Lockheed Martin Corporation - Fortune 500 1996 - Fortune","encoded_title":"Lockheed+Martin+Corporation+-+Fortune+500+1996+-+Fortune"}},{"id":368066,"post_type":"franchise-list-item","url":"\/fortune500\/1996\/united-technologies-corporation-30\/","title":"United Technologies Corporation","list_title":"Fortune 500 1996","content":"","rank":"30","thumbnail":"","featured_image":"","tables":"","buttons":"","ticker":"\u003Ctable class=\u0022tickershortcode company-market-data trend-wrapper unprocessed neutral\u0022 data-symbol=\u0022utx\u0022\u003E\n\t\t\t\t\u003Ctr\u003E\n\t\t\t\t\t\u003Ctd\u003E\u003Cspan class=\u0022ticker\u0022\u003EUTX\u003C\/span\u003E\u003C\/td\u003E\n\t\t\t\t\t\u003Ctd\u003E\u003Cspan class=\u0022tickerdata last\u0022\u003E\u003C\/span\u003E\u003Cspan class=\u0022change long\u0022\u003E\u003C\/span\u003E\u003C\/td\u003E\n\t\t\t\t\t\u003Ctd\u003E\u003Ctime class=\u0022tickerdata time\u0022\u003E\u003C\/time\u003E\u003C\/td\u003E\n\t\t\t\t\u003C\/tr\u003E\n\t\t\t\u003C\/table\u003E","ticker_text":"utx","highlights":{"Rank":"30","Previous Rank":"31","CEO":"George David","Address":"3333 Beverly Rd., Hoffman Estates, IL 60179","Website":"www.utc.com"},"linkedin":"","footnotes":"","ordering":"","year":"1996","franchise_name":"Fortune 500","right_rail_layout":"default","seo":{"seo_title":"United Technologies Corporation - Fortune 500 1996 - Fortune","seo_description":"","seo_keywords":"","seo_news_keywords":"","seo_additional_meta":""},"social":{"encoded_url":"http%3A%2F%2Ffortune.com%2Ffortune500%2F1996%2Funited-technologies-corporation-30%2F","encoded_shortlink":"http%3A%2F%2Fwp.me%2Fp4kUAt-1xKy","twitter_text":"United Technologies Corporation on the Fortune 500 1996","facebook_desc":"","facebook_title":"United Technologies Corporation - Fortune 500 1996 - Fortune","encoded_title":"United+Technologies+Corporation+-+Fortune+500+1996+-+Fortune"}},{"id":368067,"post_type":"franchise-list-item","url":"\/fortune500\/1996\/the-allstate-corporation-31\/","title":"The Allstate Corporation","list_title":"Fortune 500 1996","content":"","rank":"31","thumbnail":"","featured_image":"","tables":"","buttons":"","ticker":"\u003Ctable class=\u0022tickershortcode company-market-data trend-wrapper unprocessed neutral\u0022 data-symbol=\u0022all\u0022\u003E\n\t\t\t\t\u003Ctr\u003E\n\t\t\t\t\t\u003Ctd\u003E\u003Cspan class=\u0022ticker\u0022\u003EALL\u003C\/span\u003E\u003C\/td\u003E\n\t\t\t\t\t\u003Ctd\u003E\u003Cspan class=\u0022tickerdata last\u0022\u003E\u003C\/span\u003E\u003Cspan class=\u0022change long\u0022\u003E\u003C\/span\u003E\u003C\/td\u003E\n\t\t\t\t\t\u003Ctd\u003E\u003Ctime class=\u0022tickerdata time\u0022\u003E\u003C\/time\u003E\u003C\/td\u003E\n\t\t\t\t\u003C\/tr\u003E\n\t\t\t\u003C\/table\u003E","ticker_text":"all","highlights":{"Rank":"31","Previous Rank":"-","CEO":"Jerry Choate","Address":"1 Procter \u0026 Gamble Plaza, Cincinnati, OH 45202","Website":"www.allstate.com"},"linkedin":"","footnotes":"","ordering":"","year":"1996","franchise_name":"Fortune 500","right_rail_layout":"default","seo":{"seo_title":"The Allstate Corporation - Fortune 500 1996 - Fortune","seo_description":"","seo_keywords":"","seo_news_keywords":"","seo_additional_meta":""},"social":{"encoded_url":"http%3A%2F%2Ffortune.com%2Ffortune500%2F1996%2Fthe-allstate-corporation-31%2F","encoded_shortlink":"http%3A%2F%2Fwp.me%2Fp4kUAt-1xKz","twitter_text":"The Allstate Corporation on the Fortune 500 1996","facebook_desc":"","facebook_title":"The Allstate Corporation - Fortune 500 1996 - Fortune","encoded_title":"The+Allstate+Corporation+-+Fortune+500+1996+-+Fortune"}},{"id":368068,"post_type":"franchise-list-item","url":"\/fortune500\/1996\/federal-national-mortgage-association-32\/","title":"Federal National Mortgage Association","list_title":"Fortune 500 1996","content":"","rank":"32","thumbnail":"","featured_image":"","tables":"","buttons":"","ticker":"\u003Ctable class=\u0022tickershortcode company-market-data trend-wrapper unprocessed neutral\u0022 data-symbol=\u0022fnm\u0022\u003E\n\t\t\t\t\u003Ctr\u003E\n\t\t\t\t\t\u003Ctd\u003E\u003Cspan class=\u0022ticker\u0022\u003EFNM\u003C\/span\u003E\u003C\/td\u003E\n\t\t\t\t\t\u003Ctd\u003E\u003Cspan class=\u0022tickerdata last\u0022\u003E\u003C\/span\u003E\u003Cspan class=\u0022change long\u0022\u003E\u003C\/span\u003E\u003C\/td\u003E\n\t\t\t\t\t\u003Ctd\u003E\u003Ctime class=\u0022tickerdata time\u0022\u003E\u003C\/time\u003E\u003C\/td\u003E\n\t\t\t\t\u003C\/tr\u003E\n\t\t\t\u003C\/table\u003E","ticker_text":"fnm","highlights":{"Rank":"32","Previous Rank":"36","CEO":"James A. Johnson","Address":"8200 Jones Branch Dr., McLean, VA 22102","Website":"www.fanniemae.com"},"linkedin":"","footnotes":"","ordering":"","year":"1996","franchise_name":"Fortune 500","right_rail_layout":"default","seo":{"seo_title":"Federal National Mortgage Association - Fortune 500 1996 - Fortune","seo_description":"","seo_keywords":"","seo_news_keywords":"","seo_additional_meta":""},"social":{"encoded_url":"http%3A%2F%2Ffortune.com%2Ffortune500%2F1996%2Ffederal-national-mortgage-association-32%2F","encoded_shortlink":"http%3A%2F%2Fwp.me%2Fp4kUAt-1xKA","twitter_text":"Federal National Mortgage Association on the Fortune 500 1996","facebook_desc":"","facebook_title":"Federal National Mortgage Association - Fortune 500 1996 - Fortune","encoded_title":"Federal+National+Mortgage+Association+-+Fortune+500+1996+-+Fortune"}},{"id":368069,"post_type":"franchise-list-item","url":"\/fortune500\/1996\/merrill-lynch-company-inc-33\/","title":"Merrill Lynch \u0026 Company, Inc.","list_title":"Fortune 500 1996","content":"","rank":"33","thumbnail":"","featured_image":"","tables":"","buttons":"","ticker":"\u003Ctable class=\u0022tickershortcode company-market-data trend-wrapper unprocessed neutral\u0022 data-symbol=\u0022mer\u0022\u003E\n\t\t\t\t\u003Ctr\u003E\n\t\t\t\t\t\u003Ctd\u003E\u003Cspan class=\u0022ticker\u0022\u003EMER\u003C\/span\u003E\u003C\/td\u003E\n\t\t\t\t\t\u003Ctd\u003E\u003Cspan class=\u0022tickerdata last\u0022\u003E\u003C\/span\u003E\u003Cspan class=\u0022change long\u0022\u003E\u003C\/span\u003E\u003C\/td\u003E\n\t\t\t\t\t\u003Ctd\u003E\u003Ctime class=\u0022tickerdata time\u0022\u003E\u003C\/time\u003E\u003C\/td\u003E\n\t\t\t\t\u003C\/tr\u003E\n\t\t\t\u003C\/table\u003E","ticker_text":"mer","highlights":{"Rank":"33","Previous Rank":"40","CEO":"Daniel P. Tully","Address":"999 Lake Dr., Issaquah, WA 98027","Website":"www.ml.com"},"linkedin":"","footnotes":"","ordering":"","year":"1996","franchise_name":"Fortune 500","right_rail_layout":"default","seo":{"seo_title":"Merrill Lynch \u0026 Company, Inc. - Fortune 500 1996 - Fortune","seo_description":"","seo_keywords":"","seo_news_keywords":"","seo_additional_meta":""},"social":{"encoded_url":"http%3A%2F%2Ffortune.com%2Ffortune500%2F1996%2Fmerrill-lynch-company-inc-33%2F","encoded_shortlink":"http%3A%2F%2Fwp.me%2Fp4kUAt-1xKB","twitter_text":"Merrill Lynch \u0026 Company, Inc. on the Fortune 500 1996","facebook_desc":"","facebook_title":"Merrill Lynch \u0026 Company, Inc. - Fortune 500 1996 - Fortune","encoded_title":"Merrill+Lynch+%26+Company%2C+Inc.+-+Fortune+500+1996+-+Fortune"}},{"id":368070,"post_type":"franchise-list-item","url":"\/fortune500\/1996\/j-c-penney-company-inc-34\/","title":"J.C. Penney Company, Inc.","list_title":"Fortune 500 1996","content":"","rank":"34","thumbnail":"","featured_image":"","tables":"","buttons":"","ticker":"\u003Ctable class=\u0022tickershortcode company-market-data trend-wrapper unprocessed neutral\u0022 data-symbol=\u0022jcp\u0022\u003E\n\t\t\t\t\u003Ctr\u003E\n\t\t\t\t\t\u003Ctd\u003E\u003Cspan class=\u0022ticker\u0022\u003EJCP\u003C\/span\u003E\u003C\/td\u003E\n\t\t\t\t\t\u003Ctd\u003E\u003Cspan class=\u0022tickerdata last\u0022\u003E\u003C\/span\u003E\u003Cspan class=\u0022change long\u0022\u003E\u003C\/span\u003E\u003C\/td\u003E\n\t\t\t\t\t\u003Ctd\u003E\u003Ctime class=\u0022tickerdata time\u0022\u003E\u003C\/time\u003E\u003C\/td\u003E\n\t\t\t\t\u003C\/tr\u003E\n\t\t\t\u003C\/table\u003E","ticker_text":"jcp","highlights":{"Rank":"34","Previous Rank":"32","CEO":"James E. Oesterreicher","Address":"1 Johnson \u0026 Johnson Plaza, New Brunswick, NJ 8933","Website":"www.jcpenney.com"},"linkedin":"","footnotes":"","ordering":"","year":"1996","franchise_name":"Fortune 500","right_rail_layout":"default","seo":{"seo_title":"J.C. Penney Company, Inc. - Fortune 500 1996 - Fortune","seo_description":"","seo_keywords":"","seo_news_keywords":"","seo_additional_meta":""},"social":{"encoded_url":"http%3A%2F%2Ffortune.com%2Ffortune500%2F1996%2Fj-c-penney-company-inc-34%2F","encoded_shortlink":"http%3A%2F%2Fwp.me%2Fp4kUAt-1xKC","twitter_text":"J.C. Penney Company, Inc. on the Fortune 500 1996","facebook_desc":"","facebook_title":"J.C. Penney Company, Inc. - Fortune 500 1996 - Fortune","encoded_title":"J.C.+Penney+Company%2C+Inc.+-+Fortune+500+1996+-+Fortune"}},{"id":368071,"post_type":"franchise-list-item","url":"\/fortune500\/1996\/united-parcel-service-of-america-inc-35\/","title":"United Parcel Service of America, Inc.","list_title":"Fortune 500 1996","content":"","rank":"35","thumbnail":"","featured_image":"","tables":"","buttons":"","ticker":"","ticker_text":"","highlights":{"Rank":"35","Previous Rank":"35","CEO":"Oz Nelson","Address":"250 Parkcenter Blvd., Boise, ID 83726","Website":"www.ups.com"},"linkedin":"","footnotes":"","ordering":"","year":"1996","franchise_name":"Fortune 500","seo":{"seo_title":"United Parcel Service of America, Inc. - Fortune 500 1996 - Fortune","seo_description":"","seo_keywords":"","seo_news_keywords":"","seo_additional_meta":""},"social":{"encoded_url":"http%3A%2F%2Ffortune.com%2Ffortune500%2F1996%2Funited-parcel-service-of-america-inc-35%2F","encoded_shortlink":"http%3A%2F%2Fwp.me%2Fp4kUAt-1xKD","twitter_text":"United Parcel Service of America, Inc. on the Fortune 500 1996","facebook_desc":"","facebook_title":"United Parcel Service of America, Inc. - Fortune 500 1996 - Fortune","encoded_title":"United+Parcel+Service+of+America%2C+Inc.+-+Fortune+500+1996+-+Fortune"}},{"id":368072,"post_type":"franchise-list-item","url":"\/fortune500\/1996\/the-dow-chemical-company-36\/","title":"The Dow Chemical Company","list_title":"Fortune 500 1996","content":"","rank":"36","thumbnail":"","featured_image":"","tables":"","buttons":"","ticker":"\u003Ctable class=\u0022tickershortcode company-market-data trend-wrapper unprocessed neutral\u0022 data-symbol=\u0022dow\u0022\u003E\n\t\t\t\t\u003Ctr\u003E\n\t\t\t\t\t\u003Ctd\u003E\u003Cspan class=\u0022ticker\u0022\u003EDOW\u003C\/span\u003E\u003C\/td\u003E\n\t\t\t\t\t\u003Ctd\u003E\u003Cspan class=\u0022tickerdata last\u0022\u003E\u003C\/span\u003E\u003Cspan class=\u0022change long\u0022\u003E\u003C\/span\u003E\u003C\/td\u003E\n\t\t\t\t\t\u003Ctd\u003E\u003Ctime class=\u0022tickerdata time\u0022\u003E\u003C\/time\u003E\u003C\/td\u003E\n\t\t\t\t\u003C\/tr\u003E\n\t\t\t\u003C\/table\u003E","ticker_text":"dow","highlights":{"Rank":"36","Previous Rank":"33","CEO":"William F. Stavropoulos","Address":"1 Dell Way, Round Rock, TX 78682","Website":"www.dow.com"},"linkedin":"","footnotes":"","ordering":"","year":"1996","franchise_name":"Fortune 500","right_rail_layout":"default","seo":{"seo_title":"The Dow Chemical Company - Fortune 500 1996 - Fortune","seo_description":"","seo_keywords":"","seo_news_keywords":"","seo_additional_meta":""},"social":{"encoded_url":"http%3A%2F%2Ffortune.com%2Ffortune500%2F1996%2Fthe-dow-chemical-company-36%2F","encoded_shortlink":"http%3A%2F%2Fwp.me%2Fp4kUAt-1xKE","twitter_text":"The Dow Chemical Company on the Fortune 500 1996","facebook_desc":"","facebook_title":"The Dow Chemical Company - Fortune 500 1996 - Fortune","encoded_title":"The+Dow+Chemical+Company+-+Fortune+500+1996+-+Fortune"}},{"id":368073,"post_type":"franchise-list-item","url":"\/fortune500\/1996\/bankamerica-corporation-37\/","title":"BankAmerica Corporation","list_title":"Fortune 500 1996","content":"","rank":"37","thumbnail":"","featured_image":"","tables":"","buttons":"","ticker":"\u003Ctable class=\u0022tickershortcode company-market-data trend-wrapper unprocessed neutral\u0022 data-symbol=\u0022bac\u0022\u003E\n\t\t\t\t\u003Ctr\u003E\n\t\t\t\t\t\u003Ctd\u003E\u003Cspan class=\u0022ticker\u0022\u003EBAC\u003C\/span\u003E\u003C\/td\u003E\n\t\t\t\t\t\u003Ctd\u003E\u003Cspan class=\u0022tickerdata last\u0022\u003E\u003C\/span\u003E\u003Cspan class=\u0022change long\u0022\u003E\u003C\/span\u003E\u003C\/td\u003E\n\t\t\t\t\t\u003Ctd\u003E\u003Ctime class=\u0022tickerdata time\u0022\u003E\u003C\/time\u003E\u003C\/td\u003E\n\t\t\t\t\u003C\/tr\u003E\n\t\t\t\u003C\/table\u003E","ticker_text":"bac","highlights":{"Rank":"37","Previous Rank":"46","CEO":"David A. Coulter","Address":"235 E. 42nd St., New York, NY 10017","Website":"www.bankamerica.com"},"linkedin":"","footnotes":"","ordering":"","year":"1996","franchise_name":"Fortune 500","right_rail_layout":"default","seo":{"seo_title":"BankAmerica Corporation - Fortune 500 1996 - Fortune","seo_description":"","seo_keywords":"","seo_news_keywords":"","seo_additional_meta":""},"social":{"encoded_url":"http%3A%2F%2Ffortune.com%2Ffortune500%2F1996%2Fbankamerica-corporation-37%2F","encoded_shortlink":"http%3A%2F%2Fwp.me%2Fp4kUAt-1xKF","twitter_text":"BankAmerica Corporation on the Fortune 500 1996","facebook_desc":"","facebook_title":"BankAmerica Corporation - Fortune 500 1996 - Fortune","encoded_title":"BankAmerica+Corporation+-+Fortune+500+1996+-+Fortune"}},{"id":368074,"post_type":"franchise-list-item","url":"\/fortune500\/1996\/gte-corporation-38\/","title":"GTE Corporation","list_title":"Fortune 500 1996","content":"","rank":"38","thumbnail":"","featured_image":"","tables":"","buttons":"","ticker":"\u003Ctable class=\u0022tickershortcode company-market-data trend-wrapper unprocessed neutral\u0022 data-symbol=\u0022gte\u0022\u003E\n\t\t\t\t\u003Ctr\u003E\n\t\t\t\t\t\u003Ctd\u003E\u003Cspan class=\u0022ticker\u0022\u003EGTE\u003C\/span\u003E\u003C\/td\u003E\n\t\t\t\t\t\u003Ctd\u003E\u003Cspan class=\u0022tickerdata last\u0022\u003E\u003C\/span\u003E\u003Cspan class=\u0022change long\u0022\u003E\u003C\/span\u003E\u003C\/td\u003E\n\t\t\t\t\t\u003Ctd\u003E\u003Ctime class=\u0022tickerdata time\u0022\u003E\u003C\/time\u003E\u003C\/td\u003E\n\t\t\t\t\u003C\/tr\u003E\n\t\t\t\u003C\/table\u003E","ticker_text":"gte","highlights":{"Rank":"38","Previous Rank":"34","CEO":"Charles R. Lee","Address":"1 Madison Ave., New York, NY 10010","Website":"www.gte.com"},"linkedin":"","footnotes":"","ordering":"","year":"1996","franchise_name":"Fortune 500","right_rail_layout":"default","seo":{"seo_title":"GTE Corporation - Fortune 500 1996 - Fortune","seo_description":"","seo_keywords":"","seo_news_keywords":"","seo_additional_meta":""},"social":{"encoded_url":"http%3A%2F%2Ffortune.com%2Ffortune500%2F1996%2Fgte-corporation-38%2F","encoded_shortlink":"http%3A%2F%2Fwp.me%2Fp4kUAt-1xKG","twitter_text":"GTE Corporation on the Fortune 500 1996","facebook_desc":"","facebook_title":"GTE Corporation - Fortune 500 1996 - Fortune","encoded_title":"GTE+Corporation+-+Fortune+500+1996+-+Fortune"}},{"id":368075,"post_type":"franchise-list-item","url":"\/fortune500\/1996\/international-paper-company-39\/","title":"International Paper Company","list_title":"Fortune 500 1996","content":"","rank":"39","thumbnail":"","featured_image":"","tables":"","buttons":"","ticker":"\u003Ctable class=\u0022tickershortcode company-market-data trend-wrapper unprocessed neutral\u0022 data-symbol=\u0022ip\u0022\u003E\n\t\t\t\t\u003Ctr\u003E\n\t\t\t\t\t\u003Ctd\u003E\u003Cspan class=\u0022ticker\u0022\u003EIP\u003C\/span\u003E\u003C\/td\u003E\n\t\t\t\t\t\u003Ctd\u003E\u003Cspan class=\u0022tickerdata last\u0022\u003E\u003C\/span\u003E\u003Cspan class=\u0022change long\u0022\u003E\u003C\/span\u003E\u003C\/td\u003E\n\t\t\t\t\t\u003Ctd\u003E\u003Ctime class=\u0022tickerdata time\u0022\u003E\u003C\/time\u003E\u003C\/td\u003E\n\t\t\t\t\u003C\/tr\u003E\n\t\t\t\u003C\/table\u003E","ticker_text":"ip","highlights":{"Rank":"39","Previous Rank":"60","CEO":"John T. Dillon","Address":"3100 W. Big Beaver Rd., Troy, MI 48084","Website":"www.internationalpaper.com"},"linkedin":"","footnotes":"","ordering":"","year":"1996","franchise_name":"Fortune 500","right_rail_layout":"default","seo":{"seo_title":"International Paper Company - Fortune 500 1996 - Fortune","seo_description":"","seo_keywords":"","seo_news_keywords":"","seo_additional_meta":""},"social":{"encoded_url":"http%3A%2F%2Ffortune.com%2Ffortune500%2F1996%2Finternational-paper-company-39%2F","encoded_shortlink":"http%3A%2F%2Fwp.me%2Fp4kUAt-1xKH","twitter_text":"International Paper Company on the Fortune 500 1996","facebook_desc":"","facebook_title":"International Paper Company - Fortune 500 1996 - Fortune","encoded_title":"International+Paper+Company+-+Fortune+500+1996+-+Fortune"}},{"id":368076,"post_type":"franchise-list-item","url":"\/fortune500\/1996\/the-boeing-company-40\/","title":"The Boeing Company","list_title":"Fortune 500 1996","content":"","rank":"40","thumbnail":"","featured_image":"","tables":"","buttons":"","ticker":"\u003Ctable class=\u0022tickershortcode company-market-data trend-wrapper unprocessed neutral\u0022 data-symbol=\u0022ba\u0022\u003E\n\t\t\t\t\u003Ctr\u003E\n\t\t\t\t\t\u003Ctd\u003E\u003Cspan class=\u0022ticker\u0022\u003EBA\u003C\/span\u003E\u003C\/td\u003E\n\t\t\t\t\t\u003Ctd\u003E\u003Cspan class=\u0022tickerdata last\u0022\u003E\u003C\/span\u003E\u003Cspan class=\u0022change long\u0022\u003E\u003C\/span\u003E\u003C\/td\u003E\n\t\t\t\t\t\u003Ctd\u003E\u003Ctime class=\u0022tickerdata time\u0022\u003E\u003C\/time\u003E\u003C\/td\u003E\n\t\t\t\t\u003C\/tr\u003E\n\t\t\t\u003C\/table\u003E","ticker_text":"ba","highlights":{"Rank":"40","Previous Rank":"29","CEO":"Frank A. Shrontz","Address":"1585 Broadway, New York, NY 10036","Website":"www.boeing.com"},"linkedin":"","footnotes":"","ordering":"","year":"1996","franchise_name":"Fortune 500","right_rail_layout":"default","seo":{"seo_title":"The Boeing Company - Fortune 500 1996 - Fortune","seo_description":"","seo_keywords":"","seo_news_keywords":"","seo_additional_meta":""},"social":{"encoded_url":"http%3A%2F%2Ffortune.com%2Ffortune500%2F1996%2Fthe-boeing-company-40%2F","encoded_shortlink":"http%3A%2F%2Fwp.me%2Fp4kUAt-1xKI","twitter_text":"The Boeing Company on the Fortune 500 1996","facebook_desc":"","facebook_title":"The Boeing Company - Fortune 500 1996 - Fortune","encoded_title":"The+Boeing+Company+-+Fortune+500+1996+-+Fortune"}}]}